google_wallet_webhook_auth/__init__.py
google_wallet_webhook_auth/cache.py
google_wallet_webhook_auth/crypto.py
google_wallet_webhook_auth/exceptions.py
google_wallet_webhook_auth/validator.py
google_wallet_webhook_auth-1.0.0.dist-info/licenses/LICENSE
google_wallet_webhook_auth-1.0.0.dist-info/WHEEL
google_wallet_webhook_auth-1.0.0.dist-info/METADATA
google_wallet_webhook_auth-1.0.0.dist-info/RECORD
